streamlit_label_kit/__init__.py
streamlit_label_kit/LabelToolKit/__init__.py
streamlit_label_kit/LabelToolKit/annotation.py
streamlit_label_kit/LabelToolKit/detection.py
streamlit_label_kit/LabelToolKit/segmentation.py
streamlit_label_kit/LabelToolKit/frontend/build/asset-manifest.json
streamlit_label_kit/LabelToolKit/frontend/build/bootstrap.min.css
streamlit_label_kit/LabelToolKit/frontend/build/index.html
streamlit_label_kit/LabelToolKit/frontend/build/static/js/main.9e63099d.js
streamlit_label_kit/LabelToolKit/frontend/build/static/js/main.9e63099d.js.LICENSE.txt
streamlit_label_kit/LabelToolKit/frontend/build/static/js/main.9e63099d.js.map
streamlit_label_kit-0.1.3.dist-info/LICENSE
streamlit_label_kit-0.1.3.dist-info/METADATA
streamlit_label_kit-0.1.3.dist-info/WHEEL
streamlit_label_kit-0.1.3.dist-info/top_level.txt
streamlit_label_kit-0.1.3.dist-info/RECORD
