Metadata-Version: 2.2
Name: streamlit-label-kit
Version: 0.1.3
Summary: Streamlit components for general labeling
Author-email: Carnegie Mellon University <satya+group@cs.cmu.edu>, Jinho Yi <jinhoy@andrew.cmu.edu>
Project-URL: Homepage, https://github.com/cmusatyalab/streamlit-label-kit
Project-URL: Repository, https://github.com/cmusatyalab/streamlit-label-kit.git
Keywords: Python,Streamlit,React,JavaScript
Classifier: Development Status :: 4 - Beta
Classifier: Intended Audience :: Developers
Classifier: License :: OSI Approved :: GNU General Public License v2 (GPLv2)
Classifier: Programming Language :: Python :: 3
Classifier: Programming Language :: Python :: 3.6
Classifier: Programming Language :: Python :: 3.7
Classifier: Programming Language :: Python :: 3.8
Classifier: Programming Language :: Python :: 3.9
Classifier: Programming Language :: Python :: 3.10
Classifier: Programming Language :: Python :: 3.11
Classifier: Programming Language :: Python :: 3.12
Requires-Python: >=3.8
License-File: LICENSE
Requires-Dist: Pillow>=6.2.0
Requires-Dist: matplotlib>=3.5.3
Requires-Dist: numpy>=1
Requires-Dist: streamlit>=1.26.0
